[
  {
    "full_name": "dailydotdev/daily",
    "stargazers_count": 3627,
    "open_issues_count": 21,
    "forks_count": 177
  },
  {
    "full_name": "rodrigo-brito/ninjabot",
    "stargazers_count": 819,
    "open_issues_count": 4,
    "forks_count": 43
  },
  {
    "full_name": "diamondburned/arikawa",
    "stargazers_count": 179,
    "open_issues_count": 17,
    "forks_count": 28
  },
  {
    "full_name": "bwmarrin/discordgo",
    "stargazers_count": 2149,
    "open_issues_count": 83,
    "forks_count": 418
  },
  {
    "full_name": "open-sauced/open-sauced",
    "stargazers_count": 457,
    "open_issues_count": 45,
    "forks_count": 132
  },
  {
    "full_name": "CyberPunkMetalHead/Binance-volatility-trading-bot",
    "stargazers_count": 2556,
    "open_issues_count": 9,
    "forks_count": 466
  }
]